mystjs/__init__.py
mystjs/version.py
mystjs-0.0.1.dist-info/LICENSE
mystjs-0.0.1.dist-info/METADATA
mystjs-0.0.1.dist-info/WHEEL
mystjs-0.0.1.dist-info/top_level.txt
mystjs-0.0.1.dist-info/RECORD
