Metadata-Version: 2.1
Name: mystjs
Version: 0.0.1
Summary: Javascript based tool chain and command line for MyST
Home-page: https://myst.tools
Author: Executable Books Project
Author-email: executablebooks@gmail.com
Classifier: Development Status :: 4 - Beta
Classifier: License :: OSI Approved :: MIT License
Classifier: Programming Language :: Python :: 3.7
Classifier: Topic :: Text Processing :: Markup
Classifier: Intended Audience :: Education
Classifier: Intended Audience :: Science/Research
Classifier: Intended Audience :: Information Technology
Requires-Python: >=3.7
License-File: LICENSE
